mmh3cffi/__init__.py
mmh3cffi/_cimpl.so
mmh3cffi-0.1.1.dist-info/LICENSE
mmh3cffi-0.1.1.dist-info/METADATA
mmh3cffi-0.1.1.dist-info/WHEEL
mmh3cffi-0.1.1.dist-info/top_level.txt
mmh3cffi-0.1.1.dist-info/RECORD
