Metadata-Version: 2.1
Name: mmh3cffi
Version: 0.1.1
Summary: CFFI interface to murmurhash3/32 from aappleby/smhasher
Home-page: https://github.com/splitio/mmh3cffi
Author: Split software
Author-email: python@split.io
License: Apache 2.0
Platform: UNKNOWN
Requires-Dist: cffi (>=1.4.0)
Requires-Dist: future
